awsflock/__init__.py
awsflock/acquire.py
awsflock/common.py
awsflock/create_table.py
awsflock/main.py
awsflock/parsing.py
awsflock/release.py
awsflock/renew.py
awsflock/shared_opts.py
awsflock-0.2.0.dist-info/entry_points.txt
awsflock-0.2.0.dist-info/LICENSE
awsflock-0.2.0.dist-info/WHEEL
awsflock-0.2.0.dist-info/METADATA
awsflock-0.2.0.dist-info/RECORD
