Metadata-Version: 2.1
Name: awsflock
Version: 0.2.0
Summary: Simple locking in AWS
License: Apache 2.0
Author: Stephen Rosen
Author-email: sirosen@globus.org
Requires-Python: >=3.6,<4.0
Classifier: License :: Other/Proprietary License
Classifier: Programming Language :: Python :: 3
Classifier: Programming Language :: Python :: 3.6
Classifier: Programming Language :: Python :: 3.7
Classifier: Programming Language :: Python :: 3.8
Classifier: Programming Language :: Python :: 3.9
Requires-Dist: boto3 (>=1.16.47,<2.0.0)
Requires-Dist: click (>=7.1.2,<8.0.0)
